jsonschema_cli/__init__.py
jsonschema_cli/__main__.py
jsonschema_cli/args.py
jsonschema_cli/cli.py
jsonschema_cli/exceptions.py
jsonschema_cli/handlers.py
jsonschema_cli/load.py
jsonschema_cli/resolvers.py
jsonschema_cli/tests/test_cli.py
jsonschema_cli-0.6.2.dist-info/entry_points.txt
jsonschema_cli-0.6.2.dist-info/LICENSE
jsonschema_cli-0.6.2.dist-info/WHEEL
jsonschema_cli-0.6.2.dist-info/METADATA
jsonschema_cli-0.6.2.dist-info/RECORD
