Metadata-Version: 2.1
Name: jsonschema-cli
Version: 0.6.2
Summary: A thin wrapper over [Python Jsonschema](https://github.com/Julian/jsonschema) to allow validating shcemas easily using simple CLI commands.
Author: Eyal Mor
Author-email: eyalmor94@gmail.com
Requires-Python: >=3.6,<4.0
Classifier: Programming Language :: Python :: 3
Classifier: Programming Language :: Python :: 3.6
Classifier: Programming Language :: Python :: 3.7
Classifier: Programming Language :: Python :: 3.8
Requires-Dist: jsonschema (>=3.2.0,<4.0.0)
Requires-Dist: pyyaml (>=5.3.1,<6.0.0)
